{"resource/assets/preloading/nanzhu/zloading_tex.json":["resource/assets/preloading/nanzhu/zloading_tex/",[]],"resource/atlas/resource/assets/base.json":["resource/assets/base/",["game_panel_db.png","tips_mengban.png"]],"resource/atlas/resource/assets/img/choose/01.json":["resource/assets/img/choose/01/",["c1cg.png","c1sb1.png","icon1_1.png","icon1_2.png"]],"resource/atlas/resource/assets/img/choose/02.json":["resource/assets/img/choose/02/",["c2cg.png","c2sb1.png","icon2_1.png","icon2_2.png"]],"resource/atlas/resource/assets/img/choose/03.json":["resource/assets/img/choose/03/",["c3cg.png","c3sb1.png","icon3_1.png","icon3_2.png","icon3_3.png","icon3_4.png"]],"resource/atlas/resource/assets/img/choose/04.json":["resource/assets/img/choose/04/",["c4cg.png","c4sb1.png","icon4_1.png","icon4_2.png","icon4_3.png","icon4_4.png"]],"resource/atlas/resource/assets/img/choose/05.json":["resource/assets/img/choose/05/",["c5cg.png","c5sb1.png","c5sb2.png","icon5_1.png","icon5_2.png","icon5_3.png","icon5_4.png"]],"resource/atlas/resource/assets/img/choose/06.json":["resource/assets/img/choose/06/",["c6cg.png","c6sb1.png","icon6_1.png","icon6_2.png","icon6_3.png","icon6_4.png","icon6_5.png","icon6_6.png"]],"resource/atlas/resource/assets/img/choose/07.json":["resource/assets/img/choose/07/",["c7cg.png","c7sb1.png","icon7_1.png","icon7_2.png","icon7_3.png","icon7_4.png","icon7_5.png","icon7_6.png"]],"resource/atlas/resource/assets/img/choose/08.json":["resource/assets/img/choose/08/",["c8cg.png","c8sb1.png","icon8_1.png","icon8_2.png","icon8_3.png","icon8_4.png","icon8_5.png","icon8_6.png"]],"resource/atlas/resource/assets/img/choose/09.json":["resource/assets/img/choose/09/",["c9cg.png","c9sb1.png","icon9_1.png","icon9_2.png","icon9_3.png","icon9_4.png","icon9_5.png","icon9_6.png"]],"resource/atlas/resource/assets/img/choose/10.json":["resource/assets/img/choose/10/",["c10cg.png","c10sb1.png","icon10_1.png","icon10_2.png","icon10_3.png","icon10_4.png","icon10_5.png","icon10_6.png"]],"resource/atlas/resource/assets/img/choose/11.json":["resource/assets/img/choose/11/",["c11cg.png","c11sb1.png","icon11_1.png","icon11_2.png","icon11_3.png","icon11_4.png","icon11_5.png","icon11_6.png"]],"resource/atlas/resource/assets/img/choose/12.json":["resource/assets/img/choose/12/",["c12cg.png","c12sb1.png","icon12_1.png","icon12_2.png","icon12_3.png","icon12_4.png","icon12_5.png","icon12_6.png"]],"resource/atlas/resource/assets/img/choose/13.json":["resource/assets/img/choose/13/",["c13cg.png","c13sb1.png","icon13_1.png","icon13_2.png","icon13_3.png","icon13_4.png"]],"resource/atlas/resource/assets/img/choose/14.json":["resource/assets/img/choose/14/",["c14cg.png","c14sb1.png","icon14_1.png","icon14_2.png","icon14_3.png","icon14_4.png"]],"resource/atlas/resource/assets/img/choose/15.json":["resource/assets/img/choose/15/",["c15cg.png","c15sb1.png","icon15_1.png","icon15_2.png","icon15_3.png","icon15_4.png"]],"resource/atlas/resource/assets/img/common/gameinterface_number1.json":["resource/assets/img/common/gameinterface_number1/",["gameinterface_number1_0.png","gameinterface_number1_1.png","gameinterface_number1_2.png","gameinterface_number1_3.png","gameinterface_number1_4.png","gameinterface_number1_5.png","gameinterface_number1_6.png","gameinterface_number1_7.png","gameinterface_number1_8.png","gameinterface_number1_9.png"]],"resource/atlas/resource/assets/img/common/level_number1.json":["resource/assets/img/common/level_number1/",["level_number1_0.png","level_number1_1.png","level_number1_2.png","level_number1_3.png","level_number1_4.png","level_number1_5.png","level_number1_6.png","level_number1_7.png","level_number1_8.png","level_number1_9.png","level_number_0.png","level_number_1.png","level_number_2.png","level_number_3.png","level_number_4.png","level_number_5.png","level_number_6.png","level_number_7.png","level_number_8.png","level_number_9.png"]],"resource/atlas/resource/assets/img/common/level_number12.json":["resource/assets/img/common/level_number12/",["level_number_0.png","level_number_1.png","level_number_2.png","level_number_3.png","level_number_4.png","level_number_5.png","level_number_6.png","level_number_7.png","level_number_8.png","level_number_9.png"]],"resource/atlas/resource/assets/img/common.json":["resource/assets/img/common/",["common_button_1.png","common_button_2.png","common_button_3.png","common_icon_1.png","common_icon_2.png","common_icon_3.png","common_icon_4.png","common_icon_5.png","comombg.png","currency_baseboard_2.png","currency_baseboard_4_2.png","currency_baseboard_4_3.png","game_button_1.png","game_button_2.png","game_button_3.png","game_line_1.png","game_panel_close.png","gaming_icon_4.png","gaming_icon_5.png","icon_1.png","maininterface_icon_6.png","maininterface_icon_7.png","sign_framebg_1.png","sign_framebg_2.png","sign_icon_gold.png","sign_icon_inter.png","sign_iconbg_1.png","succeed_icon_3.png","succeed_word_3.png","success_button_3.png"]],"resource/atlas/resource/assets/img/guessLike.json":["resource/assets/img/guessLike/",["gl_icon_1.png"]],"resource/atlas/resource/assets/img/ui/addsp/power_number1.json":["resource/assets/img/ui/addsp/power_number1/",["sign_number1_0.png","sign_number1_1.png","sign_number1_2.png","sign_number1_3.png","sign_number1_4.png","sign_number1_5.png","sign_number1_6.png","sign_number1_7.png","sign_number1_8.png","sign_number1_9.png"]],"resource/atlas/resource/assets/img/ui/addsp.json":["resource/assets/img/ui/addsp/",["power_icon_1.png","power_word_1.png","power_word_2.png","power_word_51.png"]],"resource/atlas/resource/assets/img/ui/game/gameinterface_number1.json":["resource/assets/img/ui/game/gameinterface_number1/",["gameinterface_number1_0.png","gameinterface_number1_1.png","gameinterface_number1_2.png","gameinterface_number1_3.png","gameinterface_number1_4.png","gameinterface_number1_5.png","gameinterface_number1_6.png","gameinterface_number1_7.png","gameinterface_number1_8.png","gameinterface_number1_9.png"]],"resource/atlas/resource/assets/img/ui/game.json":["resource/assets/img/ui/game/",["game_icon_3.png","game_icon_4.png","game_icon_5.png","gameinterface_baseboard_1.png","gameinterface_baseboard_2.png","gameinterface_baseboard_4.png","gameinterface_baseboard_5.png","gameinterface_baseboard_6.png","gameinterface_baseboard_7.png","gameinterface_baseboard_8.png","gameinterface_icon_1.png","gameinterface_icon_2.png","gameinterface_icon_4.png","gameinterface_icon_5.png","gameinterface_word_1.png","gameinterface_word_2.png","gameinterface_word_3.png"]],"resource/atlas/resource/assets/img/ui/gamehome/currency_number.json":["resource/assets/img/ui/gamehome/currency_number/",["currency_number_0.png","currency_number_1.png","currency_number_2.png","currency_number_3.png","currency_number_4.png","currency_number_5.png","currency_number_6.png","currency_number_7.png","currency_number_8.png","currency_number_9.png"]],"resource/atlas/resource/assets/img/ui/gamehome/maininterface_number1.json":["resource/assets/img/ui/gamehome/maininterface_number1/",["maininterface_number1_0.png","maininterface_number1_1.png","maininterface_number1_2.png","maininterface_number1_3.png","maininterface_number1_4.png","maininterface_number1_5.png","maininterface_number1_6.png","maininterface_number1_7.png","maininterface_number1_8.png","maininterface_number1_9.png"]],"resource/atlas/resource/assets/img/ui/gamehome.json":["resource/assets/img/ui/gamehome/",["currency_baseboard_1.png","maininterface_add.png","maininterface_baseboard_1.png","maininterface_button_1.png","maininterface_button_1_qq.png","maininterface_button_4.png","maininterface_button_5.png","maininterface_colon.png","maininterface_icon_1.png","maininterface_icon_11.png","maininterface_icon_1_qq.png","maininterface_icon_2.png","maininterface_icon_2_qq.png","maininterface_icon_3.png","maininterface_icon_3_qq.png","maininterface_icon_4.png","maininterface_icon_4_qq.png","maininterface_icon_6.png","maininterface_line_1.png","maininterface_logo_1.png","maininterface_sign_1.png","maininterface_word_1.png","maininterface_word_2.png","more_button_1.png","more_icon.png","more_icon_1.png"]],"resource/atlas/resource/assets/img/ui/invite/invite_number1.json":["resource/assets/img/ui/invite/invite_number1/",["invite_number1_0.png","invite_number1_1.png","invite_number1_2.png","invite_number1_3.png","invite_number1_4.png","invite_number1_5.png","invite_number1_6.png","invite_number1_7.png","invite_number1_8.png","invite_number1_9.png"]],"resource/atlas/resource/assets/img/ui/invite/invite_number2.json":["resource/assets/img/ui/invite/invite_number2/",["invitation_number2_0.png","invitation_number2_1.png","invitation_number2_2.png","invitation_number2_3.png","invitation_number2_4.png","invitation_number2_5.png","invitation_number2_6.png","invitation_number2_7.png","invitation_number2_8.png","invitation_number2_9.png"]],"resource/atlas/resource/assets/img/ui/invite.json":["resource/assets/img/ui/invite/",["invitation_word_5.png","invite_baseboard_1.png","invite_baseboard_2.png","invite_button_1.png","invite_button_2.png","invite_word_2.png","invite_word_3.png","invite_word_4.png"]],"resource/atlas/resource/assets/img/ui/levelview.json":["resource/assets/img/ui/levelview/",["level_butterfly_1.png","level_button_1.png","level_word_1.png","level_word_2.png"]],"resource/atlas/resource/assets/img/ui/moregame.json":["resource/assets/img/ui/moregame/",["mygame_baseboard_1.png","mygame_baseboard_2.png","mygame_button_1.png","mygame_line_1.png","mygame_word_1.png"]],"resource/atlas/resource/assets/img/ui/offline/offline_number.json":["resource/assets/img/ui/offline/offline_number/",["offline_number_0.png","offline_number_1.png","offline_number_2.png","offline_number_3.png","offline_number_4.png","offline_number_5.png","offline_number_6.png","offline_number_7.png","offline_number_8.png","offline_number_9.png"]],"resource/atlas/resource/assets/img/ui/offline.json":["resource/assets/img/ui/offline/",["offline_icon_1.png","offline_word_1.png","offline_word_2.png","offline_word_3.png","offline_word_4.png"]],"resource/atlas/resource/assets/img/ui/share/share_number1.json":["resource/assets/img/ui/share/share_number1/",["share_number1_0.png","share_number1_1.png","share_number1_2.png","share_number1_3.png","share_number1_4.png","share_number1_5.png","share_number1_6.png","share_number1_7.png","share_number1_8.png","share_number1_9.png"]],"resource/atlas/resource/assets/img/ui/share.json":["resource/assets/img/ui/share/",["share_word_2.png","share_word_51.png"]],"resource/atlas/resource/assets/img/ui/sign/sign_number1.json":["resource/assets/img/ui/sign/sign_number1/",["sign_number1_0.png","sign_number1_1.png","sign_number1_2.png","sign_number1_3.png","sign_number1_4.png","sign_number1_5.png","sign_number1_6.png","sign_number1_7.png","sign_number1_8.png","sign_number1_9.png"]],"resource/atlas/resource/assets/img/ui/sign/sign_number2.json":["resource/assets/img/ui/sign/sign_number2/",["sign_number2_1.png","sign_number2_2.png","sign_number2_3.png","sign_number2_4.png","sign_number2_5.png","sign_number2_6.png","sign_number2_7.png"]],"resource/atlas/resource/assets/img/ui/sign.json":["resource/assets/img/ui/sign/",["sign_baseboard_2.png","sign_baseboard_5.png","sign_baseboard_6.png","sign_baseboard_7.png","sign_button_1.png","sign_close_1.png","sign_light_1.png","sign_word_1.png","sign_word_2.png","sign_word_3.png","sign_word_4.png","sign_word_5.png","sign_word_51.png","sign_word_7.png","sign_word_8.png"]],"resource/atlas/resource/assets/img/ui/success/succeed_number1.json":["resource/assets/img/ui/success/succeed_number1/",["succeed_number1_0.png","succeed_number1_1.png","succeed_number1_2.png","succeed_number1_3.png","succeed_number1_4.png","succeed_number1_5.png","succeed_number1_6.png","succeed_number1_7.png","succeed_number1_8.png","succeed_number1_9.png"]],"resource/atlas/resource/assets/img/ui/success/succeed_number2.json":["resource/assets/img/ui/success/succeed_number2/",["succeed_number2_0.png","succeed_number2_1.png","succeed_number2_2.png","succeed_number2_3.png","succeed_number2_4.png","succeed_number2_5.png","succeed_number2_6.png","succeed_number2_7.png","succeed_number2_8.png","succeed_number2_9.png"]],"resource/atlas/resource/assets/img/ui/success/succeed_number3.json":["resource/assets/img/ui/success/succeed_number3/",["succeed_number3_0.png","succeed_number3_1.png","succeed_number3_2.png","succeed_number3_3.png","succeed_number3_4.png","succeed_number3_5.png","succeed_number3_6.png","succeed_number3_7.png","succeed_number3_8.png","succeed_number3_9.png"]],"resource/atlas/resource/assets/img/ui/success.json":["resource/assets/img/ui/success/",["box_icon_3.png","box_icon_4.png","box_icon_5.png","failure_baseboard_1.png","failure_icon_1.png","failure_icon_2.png","failure_icon_3.png","failure_word_2.png","failure_word_3.png","failure_word_4.png","failure_word_5.png","failure_word_6.png","failure_word_61.png","failure_word_8.png","succeed_icon_2.png","succeed_progressbar_1.png","succeed_word_2.png","succeed_word_3.png","succeed_word_5.png","succeed_word_6.png","succeed_word_8.png","success_word_2.png","success_word_3.png","success_word_4.png"]],"resource/atlas/resource/assets/img/wecat.json":["resource/assets/img/wecat/",["box_baseboard_1.png","box_baseboard_2.png","box_button_1.png","box_button_2.png","box_button_3.png","box_word_1.png","button.png","failed_baseboard_1.png","failed_baseboard_2.png","failed_icon_1.png","game_baseboard.png","game_baseboard_1.png","game_baseboard_1_1.png","game_button_2.png","game_button_3.png","game_icon_1.png","game_icon_1_1.png","mygame_baseboard_1.png","mygame_baseboard_2.png","mygame_button_1.png","mygame_line_1.png","mygame_word_1.png","succeed_word_1.png"]],"resource/atlas/resource/assets/platform/vivo.json":["resource/assets/platform/vivo/",["add_baseboard_1.png","add_baseboard_2.png","add_icon_2.png","add_word_1.png","maininterface_icon_2.png","power_baseboard_4.png","power_button_2.png"]],"resource/atlas/resource/assets/preloading/loading_number.json":["resource/assets/preloading/loading_number/",["loading_number_0.png","loading_number_1.png","loading_number_2.png","loading_number_3.png","loading_number_4.png","loading_number_5.png","loading_number_6.png","loading_number_7.png","loading_number_8.png","loading_number_9.png"]],"resource/atlas/resource/assets/preloading/nanzhu/library/gaoshou.json":["resource/assets/preloading/nanzhu/library/gaoshou/",["zfa.png","zpi1.png","zpi2.png","zshen1.png","ztou.png","zui6.png","zui7.png","zxue.png","zyoumei.png","zyoushou1.png","zyoushou2.png","zyoushou3.png","zyoushou4.png","zyoushou5.png","zyoutui1.png","zyoutui2.png","zyoutui3.png","zyouxiu1.png","zyouyan1.png","zyouyan2.png","zyouyan3.png","zyouyan4.png","zyouyan5.png","zyouyt1.png","zyouyt2.png","zyouyt3.png","zzui1.png","zzui2.png","zzui3.png","zzui4.png","zzui5.png","zzuomei.png","zzuoshou1.png","zzuoshou2.png","zzuoshou3.png","zzuoshou4.png","zzuotui1.png","zzuotui2.png","zzuotui3.png","zzuoxiu1.png","zzuoyan1.png","zzuoyan2.png","zzuoyan3.png","zzuoyan4.png","zzuoyan5.png","zzuoyt1.png","zzuoyt2.png","zzuoyt3.png"]],"resource/atlas/resource/assets/preloading/nvzhu/library/gaoshou.json":["resource/assets/preloading/nvzhu/library/gaoshou/",["c8sheng1.png","c8yizi.png","nfa1.png","nfa2.png","nfa3.png","nfa4.png","nqun1.png","nshen1.png","ntou.png","nyoumei.png","nyoushou1.png","nyoushou2.png","nyoushou3.png","nyoushou4.png","nyoutui1.png","nyoutui2.png","nyouxie1.png","nyouxiu1.png","nyouyan1.png","nyouyan2.png","nyouyan3.png","nyouyan4.png","nyouyt1.png","nyouyt2.png","nyouyt3.png","nzui1.png","nzui2.png","nzui3.png","nzuomei.png","nzuoshou1.png","nzuoshou2.png","nzuoshou3.png","nzuotui1.png","nzuotui2.png","nzuoxie1.png","nzuoxiu1.png","nzuoyan1.png","nzuoyan2.png","nzuoyan3.png","nzuoyan4.png","nzuoyt1.png","nzuoyt2.png","nzuoyt3.png","shui.png"]],"resource/atlas/resource/assets/preloading/nvzhu.json":["resource/assets/preloading/nvzhu/",["nloading.png","nloading_tex.png"]]}